nvdocker/__init__.py
nvdocker/nvdocker.py
nvdocker-0.0.1.dist-info/DESCRIPTION.rst
nvdocker-0.0.1.dist-info/METADATA
nvdocker-0.0.1.dist-info/RECORD
nvdocker-0.0.1.dist-info/WHEEL
nvdocker-0.0.1.dist-info/metadata.json
nvdocker-0.0.1.dist-info/top_level.txt
