Metadata-Version: 2.0
Name: nvdocker
Version: 0.0.1
Summary: nvdocker is library built on top of the docker-py python sdk to build and run docker containers using nvidia-docker.
Home-page: https://github.com/acm-uiuc/nvdocker
Author: ACM@UIUC
Author-email: acm@illinois.edu
License: UNKNOWN
Keywords: docker nvidia-docker development containers frameworks
Platform: UNKNOWN
Classifier: Development Status :: 3 - Alpha
Classifier: Intended Audience :: Developers
Classifier: Intended Audience :: Science/Research
Classifier: Topic :: Scientific/Engineering :: Artificial Intelligence
Classifier: License :: OSI Approved :: University of Illinois/NCSA Open Source License
Classifier: Programming Language :: Python :: 2
Classifier: Programming Language :: Python :: 2.7
Classifier: Programming Language :: Python :: 3
Classifier: Programming Language :: Python :: 3.4
Classifier: Programming Language :: Python :: 3.5
Classifier: Programming Language :: Python :: 3.6
Classifier: Operating System :: POSIX :: Linux
Requires-Dist: setuptools
